verizon/__init__.py
verizon/api_helper.py
verizon/configuration.py
verizon/verizon_client.py
verizon/controllers/__init__.py
verizon/controllers/account_devices_controller.py
verizon/controllers/account_requests_controller.py
verizon/controllers/account_subscriptions_controller.py
verizon/controllers/accounts_controller.py
verizon/controllers/anomaly_settings_controller.py
verizon/controllers/anomaly_triggers_controller.py
verizon/controllers/anomaly_triggers_v2_controller.py
verizon/controllers/base_controller.py
verizon/controllers/billing_controller.py
verizon/controllers/campaigns_v2_controller.py
verizon/controllers/campaigns_v3_controller.py
verizon/controllers/client_logging_controller.py
verizon/controllers/cloud_connector_devices_controller.py
verizon/controllers/cloud_connector_subscriptions_controller.py
verizon/controllers/configuration_files_controller.py
verizon/controllers/connectivity_callbacks_controller.py
verizon/controllers/device_actions_controller.py
verizon/controllers/device_diagnostics_controller.py
verizon/controllers/device_groups_controller.py
verizon/controllers/device_location_callbacks_controller.py
verizon/controllers/device_management_controller.py
verizon/controllers/device_monitoring_controller.py
verizon/controllers/device_profile_management_controller.py
verizon/controllers/device_reports_controller.py
verizon/controllers/device_service_management_controller.py
verizon/controllers/device_sms_messaging_controller.py
verizon/controllers/devices_location_subscriptions_controller.py
verizon/controllers/devices_locations_controller.py
verizon/controllers/diagnostics_callbacks_controller.py
verizon/controllers/diagnostics_factory_reset_controller.py
verizon/controllers/diagnostics_history_controller.py
verizon/controllers/diagnostics_observations_controller.py
verizon/controllers/diagnostics_settings_controller.py
verizon/controllers/diagnostics_subscriptions_controller.py
4_g_specs_sdk-1.3.0.dist-info/LICENSE
4_g_specs_sdk-1.3.0.dist-info/METADATA
4_g_specs_sdk-1.3.0.dist-info/WHEEL
4_g_specs_sdk-1.3.0.dist-info/top_level.txt
4_g_specs_sdk-1.3.0.dist-info/RECORD
