Metadata-Version: 2.1
Name: 4-g-specs-sdk
Version: 1.3.0
Summary: Just for Validating
Author-email: Adeel Ahmed Qureshi <adeelahmedqureshi02@gmail.com>
Project-URL: Documentation, https://www.dawn.com/
Keywords: Tutorials
Requires-Python: >=3.7
License-File: LICENSE
Requires-Dist: apimatic-core ~=0.2.0
Requires-Dist: apimatic-core-interfaces ~=0.1.0
Requires-Dist: apimatic-requests-client-adapter ~=0.1.0
Requires-Dist: enum34 >=1.1.10,~=1.1
Requires-Dist: deprecation ~=2.1
Requires-Dist: python-dateutil ~=2.8.1
Provides-Extra: testutils
Requires-Dist: pytest >=7.2.2 ; extra == 'testutils'
